asy_pt/__init__.py
asy_pt/dotenv_config.py
asy_pt/es_async.py
asy_pt/json_p.py
asy_pt/logger.py
asy_pt/redis_async.py
asy_pt/response.py
asy_pt/try_cache.py
asy_pt-0.0.2.dist-info/METADATA
asy_pt-0.0.2.dist-info/WHEEL
asy_pt-0.0.2.dist-info/top_level.txt
asy_pt-0.0.2.dist-info/RECORD
