Metadata-Version: 2.1
Name: asy_pt
Version: 0.0.2
Summary: asy_pt
Home-page: https://github.com/xulehexuwei
Author: xuwei
Author-email: 15200813194@163.com
License: BSD License
Classifier: Environment :: Web Environment
Classifier: Intended Audience :: Developers
Classifier: License :: OSI Approved :: BSD License
Classifier: Operating System :: OS Independent
Classifier: Programming Language :: Python :: 3.10
Classifier: Topic :: Internet :: WWW/HTTP
Classifier: Topic :: Internet :: WWW/HTTP :: Dynamic Content
Requires-Dist: elasticsearch>=7.13.0
